aesthetic_ascii_mindaugas/__init__.py
aesthetic_ascii_mindaugas/synthesize.py
aesthetic_ascii_mindaugas-0.0.1.dist-info/LICENSE
aesthetic_ascii_mindaugas-0.0.1.dist-info/METADATA
aesthetic_ascii_mindaugas-0.0.1.dist-info/WHEEL
aesthetic_ascii_mindaugas-0.0.1.dist-info/top_level.txt
aesthetic_ascii_mindaugas-0.0.1.dist-info/RECORD
