Metadata-Version: 2.1
Name: aesthetic-ascii-mindaugas
Version: 0.0.1
Summary: For generating A E S T H E T I C ascii art
Home-page: https://github.com/
Author: Mindaugas B.
Author-email: darbas.mindaugas@gmail.com
License: UNKNOWN
Platform: UNKNOWN
Classifier: Programming Language :: Python :: 3
Classifier: License :: OSI Approved :: MIT License
Classifier: Operating System :: OS Independent
Requires-Python: >=3.7
License-File: LICENSE
